{
  "url": "http://hotlinks.ru/catalog/308/300/p34",
  "timestamp": "2025-06-04T01:21:04.813726+00:00",
  "screenshot_path": null,
  "domain_info": {
    "whois": {
      "registrar": "ARDIS-RU",
      "creation_date": "2000-02-22 14:50:26",
      "expiration_date": "2026-02-28 21:00:00",
      "name_servers": [
        "ns1.timeweb.ru.",
        "ns2.timeweb.ru.",
        "ns3.timeweb.org.",
        "ns4.timeweb.org."
      ]
    },
    "dns": {
      "a_records": [
        "92.53.96.137"
      ],
      "mx_records": [
        "10 mx1.timeweb.ru.",
        "10 mx2.timeweb.ru."
      ],
      "txt_records": [
        "\"v=spf1 include:_spf.timeweb.ru ~all\""
      ]
    },
    "age_days": 9233,
    "registrar": "ARDIS-RU",
    "name_servers": [
      "ns1.timeweb.ru.",
      "ns2.timeweb.ru.",
      "ns3.timeweb.org.",
      "ns4.timeweb.org."
    ]
  },
  "ssl_info": {
    "valid": false,
    "issuer": null,
    "subject": null,
    "not_before": null,
    "not_after": null,
    "days_remaining": null,
    "san": [],
    "issues": [
      "SSL Error: [SSL: CERTIFICATE_VERIFY_FAILED] certificate verify failed: Hostname mismatch, certificate is not valid for 'hotlinks.ru'. (_ssl.c:1129)"
    ]
  },
  "technology_stack": [
    "Server: nginx/1.26.3"
  ],
  "performance_metrics": {},
  "security_headers": {
    "score": 0.0,
    "headers_present": [],
    "headers_missing": [
      "HSTS",
      "X-Content-Type-Options",
      "X-Frame-Options",
      "CSP",
      "XSS Protection",
      "Referrer Policy"
    ],
    "issues": [
      "Missing HSTS header",
      "Missing X-Content-Type-Options header",
      "Missing X-Frame-Options header",
      "Missing CSP header",
      "Missing XSS Protection header",
      "Missing Referrer Policy header"
    ]
  },
  "visual_analysis": {}
}